suicide_text_predictor/__init__.py
suicide_text_predictor/text_prediction.pt
suicide_text_predictor/vocab.pth
suicide_text_predictor-0.2.4.dist-info/LICENSE
suicide_text_predictor-0.2.4.dist-info/METADATA
suicide_text_predictor-0.2.4.dist-info/WHEEL
suicide_text_predictor-0.2.4.dist-info/top_level.txt
suicide_text_predictor-0.2.4.dist-info/RECORD
