Metadata-Version: 2.1
Name: suicide_text_predictor
Version: 0.2.4
Summary: A package to predict if a text is a suicide post or not.
Home-page: https://github.com/ng0cduy/applied-AI
Author: Ngoc Duy Bui
Author-email: buiduyngoc1@gmail.com
Classifier: Programming Language :: Python :: 3
Classifier: License :: OSI Approved :: MIT License
Classifier: Operating System :: OS Independent
Requires-Python: >=3.7
License-File: LICENSE
Requires-Dist: torch==2.0.1
Requires-Dist: torchtext==0.15.2
